{
  "metadata": {
    "last_update": "2026-02-05T13:00:00Z",
    "country": "Portugal",
    "timezone": "Europe/Lisbon"
  },
  "events": [
  {
    "id": "20260206-laliga-celta-osasuna",
    "sport": "Futebol",
    "competition": "La Liga",
    "eventName": "Celta Vigo vs Osasuna",
    "stage": "Liga regular",
    "startTimeUtc": "2026-02-06T20:00:00Z",
    "location": "Unknown",
    "channels": [
      {
        "name": "DAZN 1",
        "type": "Subscription"
      }
    ],
    "country": "Portugal"
  },
  {
    "id": "20260206-premierleague-leeds-nottingham",
    "sport": "Futebol",
    "competition": "Premier League",
    "eventName": "Leeds vs Nottingham",
    "stage": "Liga regular",
    "startTimeUtc": "2026-02-06T20:00:00Z",
    "location": "Unknown",
    "channels": [
      {
        "name": "DAZN 1",
        "type": "Subscription"
      }
    ],
    "country": "Portugal"
  },
  {
    "id": "20260206-seriea-verona-pisa",
    "sport": "Futebol",
    "competition": "Serie A",
    "eventName": "Verona vs Pisa",
    "stage": "Liga regular",
    "startTimeUtc": "2026-02-06T19:45:00Z",
    "location": "Unknown",
    "channels": [
      {
        "name": "Sport TV 2",
        "type": "Subscription"
      }
    ],
    "country": "Portugal"
  },
  {
    "id": "20260206-ligue1-metz-lille",
    "sport": "Futebol",
    "competition": "Ligue 1",
    "eventName": "Metz vs Lille",
    "stage": "Liga regular",
    "startTimeUtc": "2026-02-06T19:45:00Z",
    "location": "Unknown",
    "channels": [
      {
        "name": "Sport TV 4",
        "type": "Subscription"
      }
    ],
    "country": "Portugal"
  },
  {
    "id": "20260206-bundesliga-unionberlin-eintracht",
    "sport": "Futebol",
    "competition": "Bundesliga",
    "eventName": "Union Berlin vs Eintracht Frankfurt",
    "stage": "Liga regular",
    "startTimeUtc": "2026-02-06T19:30:00Z",
    "location": "Unknown",
    "channels": [
      {
        "name": "DAZN 1",
        "type": "Subscription"
      }
    ],
    "country": "Portugal"
  },
  {
    "id": "20260207-lp1-moreirense-gilvicente",
    "sport": "Futebol",
    "competition": "Primeira Liga",
    "eventName": "Moreirense vs Gil Vicente",
    "stage": "Liga regular",
    "startTimeUtc": "2026-02-07T15:30:00Z",
    "location": "Unknown",
    "channels": [
      {
        "name": "Sport TV 1",
        "type": "Subscription"
      }
    ],
    "country": "Portugal"
  },
  {
    "id": "20260207-lp1-estrela-santaclara",
    "sport": "Futebol",
    "competition": "Primeira Liga",
    "eventName": "Estrela vs Santa Clara",
    "stage": "Liga regular",
    "startTimeUtc": "2026-02-07T15:30:00Z",
    "location": "Unknown",
    "channels": [
      {
        "name": "Sport TV 1",
        "type": "Subscription"
      }
    ],
    "country": "Portugal"
  },
  {
    "id": "20260207-lp1-boavista-tondela",
    "sport": "Futebol",
    "competition": "Primeira Liga",
    "eventName": "Boavista vs Tondela",
    "stage": "Liga regular",
    "startTimeUtc": "2026-02-07T18:00:00Z",
    "location": "Unknown",
    "channels": [
      {
        "name": "Sport TV 1",
        "type": "Subscription"
      }
    ],
    "country": "Portugal"
  },
  {
    "id": "20260207-lp1-amora-vitoriaguimaraes",
    "sport": "Futebol",
    "competition": "Primeira Liga",
    "eventName": "Amora vs Vitória Guimarães",
    "stage": "Liga regular",
    "startTimeUtc": "2026-02-07T20:30:00Z",
    "location": "Unknown",
    "channels": [
      {
        "name": "Sport TV 1",
        "type": "Subscription"
      }
    ],
    "country": "Portugal"
  },
  {
    "id": "20260207-laliga-rayovallecano-oviedo",
    "sport": "Futebol",
    "competition": "La Liga",
    "eventName": "Rayo Vallecano vs R. Oviedo",
    "stage": "Liga regular",
    "startTimeUtc": "2026-02-07T13:00:00Z",
    "location": "Unknown",
    "channels": [
      {
        "name": "DAZN 1",
        "type": "Subscription"
      }
    ],
    "country": "Portugal"
  },
  {
    "id": "20260207-laliga-barcelona-mallorca",
    "sport": "Futebol",
    "competition": "La Liga",
    "eventName": "Barcelona vs Mallorca",
    "stage": "Liga regular",
    "startTimeUtc": "2026-02-07T15:15:00Z",
    "location": "Unknown",
    "channels": [
      {
        "name": "DAZN 2",
        "type": "Subscription"
      }
    ],
    "country": "Portugal"
  },
  {
    "id": "20260207-laliga-sevilla-girona",
    "sport": "Futebol",
    "competition": "La Liga",
    "eventName": "Sevilla vs Girona",
    "stage": "Liga regular",
    "startTimeUtc": "2026-02-07T17:30:00Z",
    "location": "Unknown",
    "channels": [
      {
        "name": "DAZN 1",
        "type": "Subscription"
      }
    ],
    "country": "Portugal"
  },
  {
    "id": "20260207-laliga-realsociedad-elche",
    "sport": "Futebol",
    "competition": "La Liga",
    "eventName": "Real Sociedad vs Elche",
    "stage": "Liga regular",
    "startTimeUtc": "2026-02-07T20:00:00Z",
    "location": "Unknown",
    "channels": [
      {
        "name": "DAZN 1",
        "type": "Subscription"
      }
    ],
    "country": "Portugal"
  },
  {
    "id": "20260207-premierleague-manutd-tottenham",
    "sport": "Futebol",
    "competition": "Premier League",
    "eventName": "Manchester Utd vs Tottenham",
    "stage": "Liga regular",
    "startTimeUtc": "2026-02-07T13:30:00Z",
    "location": "Unknown",
    "channels": [
      {
        "name": "DAZN 1",
        "type": "Subscription"
      }
    ],
    "country": "Portugal"
  },
  {
    "id": "20260207-premierleague-arsenal-sunderland",
    "sport": "Futebol",
    "competition": "Premier League",
    "eventName": "Arsenal vs Sunderland",
    "stage": "Liga regular",
    "startTimeUtc": "2026-02-07T15:00:00Z",
    "location": "Unknown",
    "channels": [
      {
        "name": "DAZN 1",
        "type": "Subscription"
      }
    ],
    "country": "Portugal"
  },
  {
    "id": "20260207-premierleague-wolves-chelsea",
    "sport": "Futebol",
    "competition": "Premier League",
    "eventName": "Wolves vs Chelsea",
    "stage": "Liga regular",
    "startTimeUtc": "2026-02-07T15:00:00Z",
    "location": "Unknown",
    "channels": [
      {
        "name": "DAZN 1",
        "type": "Subscription"
      }
    ],
    "country": "Portugal"
  },
  {
    "id": "20260207-premierleague-newcastle-brentford",
    "sport": "Futebol",
    "competition": "Premier League",
    "eventName": "Newcastle vs Brentford",
    "stage": "Liga regular",
    "startTimeUtc": "2026-02-07T17:30:00Z",
    "location": "Unknown",
    "channels": [
      {
        "name": "DAZN 1",
        "type": "Subscription"
      }
    ],
    "country": "Portugal"
  },
  {
    "id": "20260207-seriea-genoa-napoli",
    "sport": "Futebol",
    "competition": "Serie A",
    "eventName": "Genoa vs Napoli",
    "stage": "Liga regular",
    "startTimeUtc": "2026-02-07T17:00:00Z",
    "location": "Unknown",
    "channels": [
      {
        "name": "Sport TV 4",
        "type": "Subscription"
      }
    ],
    "country": "Portugal"
  },
  {
    "id": "20260207-seriea-fiorentina-torino",
    "sport": "Futebol",
    "competition": "Serie A",
    "eventName": "Fiorentina vs Torino",
    "stage": "Liga regular",
    "startTimeUtc": "2026-02-07T19:45:00Z",
    "location": "Unknown",
    "channels": [
      {
        "name": "Sport TV 1",
        "type": "Subscription"
      }
    ],
    "country": "Portugal"
  },
  {
    "id": "20260207-ligue1-lens-nantes",
    "sport": "Futebol",
    "competition": "Ligue 1",
    "eventName": "Lens vs Nantes",
    "stage": "Liga regular",
    "startTimeUtc": "2026-02-07T16:00:00Z",
    "location": "Unknown",
    "channels": [
      {
        "name": "Sport TV 1",
        "type": "Subscription"
      }
    ],
    "country": "Portugal"
  },
  {
    "id": "20260207-ligue1-brest-lorient",
    "sport": "Futebol",
    "competition": "Ligue 1",
    "eventName": "Brest vs Lorient",
    "stage": "Liga regular",
    "startTimeUtc": "2026-02-07T18:00:00Z",
    "location": "Unknown",
    "channels": [
      {
        "name": "Sport TV 1",
        "type": "Subscription"
      }
    ],
    "country": "Portugal"
  },
  {
    "id": "20260207-ligue1-rennes-lyon",
    "sport": "Futebol",
    "competition": "Ligue 1",
    "eventName": "Rennes vs Lyon",
    "stage": "Liga regular",
    "startTimeUtc": "2026-02-07T20:05:00Z",
    "location": "Unknown",
    "channels": [
      {
        "name": "Sport TV 2",
        "type": "Subscription"
      }
    ],
    "country": "Portugal"
  },
  {
    "id": "20260207-bundesliga-wolfsburg-dortmund",
    "sport": "Futebol",
    "competition": "Bundesliga",
    "eventName": "Wolfsburg vs Dortmund",
    "stage": "Liga regular",
    "startTimeUtc": "2026-02-07T14:30:00Z",
    "location": "Unknown",
    "channels": [
      {
        "name": "DAZN 2",
        "type": "Subscription"
      }
    ],
    "country": "Portugal"
  },
  {
    "id": "20260207-bundesliga-monchengladbach-leverkusen",
    "sport": "Futebol",
    "competition": "Bundesliga",
    "eventName": "B. Monchengladbach vs Bayer Leverkusen",
    "stage": "Liga regular",
    "startTimeUtc": "2026-02-07T17:30:00Z",
    "location": "Unknown",
    "channels": [
      {
        "name": "DAZN 2",
        "type": "Subscription"
      }
    ],
    "country": "Portugal"
  },
  {
    "id": "20260208-lp1-nacional-casapia",
    "sport": "Futebol",
    "competition": "Primeira Liga",
    "eventName": "Nacional vs Casa Pia",
    "stage": "Liga regular",
    "startTimeUtc": "2026-02-08T15:30:00Z",
    "location": "Unknown",
    "channels": [
      {
        "name": "Sport TV 1",
        "type": "Subscription"
      }
    ],
    "country": "Portugal"
  },
  {
    "id": "20260208-lp1-braga-rioave",
    "sport": "Futebol",
    "competition": "Primeira Liga",
    "eventName": "Braga vs Rio Ave",
    "stage": "Liga regular",
    "startTimeUtc": "2026-02-08T18:00:00Z",
    "location": "Unknown",
    "channels": [
      {
        "name": "Sport TV 1",
        "type": "Subscription"
      }
    ],
    "country": "Portugal"
  },
  {
    "id": "20260208-lp1-benfica-arouca",
    "sport": "Futebol",
    "competition": "Primeira Liga",
    "eventName": "Benfica vs Arouca",
    "stage": "Liga regular",
    "startTimeUtc": "2026-02-08T20:30:00Z",
    "location": "Unknown",
    "channels": [
      {
        "name": "BTV",
        "type": "Subscription"
      }
    ],
    "country": "Portugal"
  },
  {
    "id": "20260208-laliga-alaves-getafe",
    "sport": "Futebol",
    "competition": "La Liga",
    "eventName": "Alaves vs Getafe",
    "stage": "Liga regular",
    "startTimeUtc": "2026-02-08T13:00:00Z",
    "location": "Unknown",
    "channels": [
      {
        "name": "DAZN 2",
        "type": "Subscription"
      }
    ],
    "country": "Portugal"
  },
  {
    "id": "20260208-laliga-bilbao-levante",
    "sport": "Futebol",
    "competition": "La Liga",
    "eventName": "Ath. Bilbao vs Levante",
    "stage": "Liga regular",
    "startTimeUtc": "2026-02-08T15:15:00Z",
    "location": "Unknown",
    "channels": [
      {
        "name": "DAZN 2",
        "type": "Subscription"
      }
    ],
    "country": "Portugal"
  },
  {
    "id": "20260208-laliga-atletico-betis",
    "sport": "Futebol",
    "competition": "La Liga",
    "eventName": "Atl. Madrid vs Betis",
    "stage": "Liga regular",
    "startTimeUtc": "2026-02-08T17:30:00Z",
    "location": "Unknown",
    "channels": [
      {
        "name": "DAZN 2",
        "type": "Subscription"
      }
    ],
    "country": "Portugal"
  },
  {
    "id": "20260208-laliga-valencia-realmadrid",
    "sport": "Futebol",
    "competition": "La Liga",
    "eventName": "Valencia vs Real Madrid",
    "stage": "Liga regular",
    "startTimeUtc": "2026-02-08T20:00:00Z",
    "location": "Unknown",
    "channels": [
      {
        "name": "DAZN 2",
        "type": "Subscription"
      }
    ],
    "country": "Portugal"
  },
  {
    "id": "20260208-premierleague-brighton-crystalpalace",
    "sport": "Futebol",
    "competition": "Premier League",
    "eventName": "Brighton vs Crystal Palace",
    "stage": "Liga regular",
    "startTimeUtc": "2026-02-08T14:00:00Z",
    "location": "Unknown",
    "channels": [
      {
        "name": "DAZN 1",
        "type": "Subscription"
      }
    ],
    "country": "Portugal"
  },
  {
    "id": "20260208-premierleague-liverpool-mancity",
    "sport": "Futebol",
    "competition": "Premier League",
    "eventName": "Liverpool vs Manchester City",
    "stage": "Liga regular",
    "startTimeUtc": "2026-02-08T16:30:00Z",
    "location": "Unknown",
    "channels": [
      {
        "name": "DAZN 1",
        "type": "Subscription"
      }
    ],
    "country": "Portugal"
  },
  {
    "id": "20260208-seriea-bologna-parma",
    "sport": "Futebol",
    "competition": "Serie A",
    "eventName": "Bologna vs Parma",
    "stage": "Liga regular",
    "startTimeUtc": "2026-02-08T11:30:00Z",
    "location": "Unknown",
    "channels": [
      {
        "name": "Sport TV 2",
        "type": "Subscription"
      }
    ],
    "country": "Portugal"
  },
  {
    "id": "20260208-seriea-lazio-udinese",
    "sport": "Futebol",
    "competition": "Serie A",
    "eventName": "Lazio vs Udinese",
    "stage": "Liga regular",
    "startTimeUtc": "2026-02-08T14:00:00Z",
    "location": "Unknown",
    "channels": [
      {
        "name": "Sport TV 2",
        "type": "Subscription"
      }
    ],
    "country": "Portugal"
  },
  {
    "id": "20260208-seriea-sassuolo-inter",
    "sport": "Futebol",
    "competition": "Serie A",
    "eventName": "Sassuolo vs Inter",
    "stage": "Liga regular",
    "startTimeUtc": "2026-02-08T17:00:00Z",
    "location": "Unknown",
    "channels": [
      {
        "name": "Sport TV 2",
        "type": "Subscription"
      }
    ],
    "country": "Portugal"
  },
  {
    "id": "20260208-seriea-juventus-lecce",
    "sport": "Futebol",
    "competition": "Serie A",
    "eventName": "Juventus vs Lecce",
    "stage": "Liga regular",
    "startTimeUtc": "2026-02-08T19:45:00Z",
    "location": "Unknown",
    "channels": [
      {
        "name": "Sport TV 2",
        "type": "Subscription"
      }
    ],
    "country": "Portugal"
  },
  {
    "id": "20260208-ligue1-nice-monaco",
    "sport": "Futebol",
    "competition": "Ligue 1",
    "eventName": "Nice vs Monaco",
    "stage": "Liga regular",
    "startTimeUtc": "2026-02-08T14:00:00Z",
    "location": "Unknown",
    "channels": [
      {
        "name": "Sport TV 1",
        "type": "Subscription"
      }
    ],
    "country": "Portugal"
  },
  {
    "id": "20260208-ligue1-lehavre-strasbourg",
    "sport": "Futebol",
    "competition": "Ligue 1",
    "eventName": "Le Havre vs Strasbourg",
    "stage": "Liga regular",
    "startTimeUtc": "2026-02-08T16:15:00Z",
    "location": "Unknown",
    "channels": [
      {
        "name": "Sport TV 3",
        "type": "Subscription"
      }
    ],
    "country": "Portugal"
  },
  {
    "id": "20260208-ligue1-psg-marseille",
    "sport": "Futebol",
    "competition": "Ligue 1",
    "eventName": "PSG vs Marseille",
    "stage": "Liga regular",
    "startTimeUtc": "2026-02-08T19:45:00Z",
    "location": "Unknown",
    "channels": [
      {
        "name": "Sport TV 1",
        "type": "Subscription"
      }
    ],
    "country": "Portugal"
  },
  {
    "id": "20260208-bundesliga-koln-leipzig",
    "sport": "Futebol",
    "competition": "Bundesliga",
    "eventName": "FC Köln vs RB Leipzig",
    "stage": "Liga regular",
    "startTimeUtc": "2026-02-08T14:30:00Z",
    "location": "Unknown",
    "channels": [
      {
        "name": "DAZN 1",
        "type": "Subscription"
      }
    ],
    "country": "Portugal"
  },
  {
    "id": "20260208-bundesliga-bayern-hoffenheim",
    "sport": "Futebol",
    "competition": "Bundesliga",
    "eventName": "Bayern Munich vs Hoffenheim",
    "stage": "Liga regular",
    "startTimeUtc": "2026-02-08T16:30:00Z",
    "location": "Unknown",
    "channels": [
      {
        "name": "DAZN 1",
        "type": "Subscription"
      }
    ],
    "country": "Portugal"
  },
  {
    "id": "20260209-lp1-famalicao-avs",
    "sport": "Futebol",
    "competition": "Primeira Liga",
    "eventName": "FC Famalicão vs AVS Futebol",
    "stage": "Liga regular",
    "startTimeUtc": "2026-02-09T18:45:00Z",
    "location": "Unknown",
    "channels": [
      {
        "name": "Sport TV 2",
        "type": "Subscription"
      }
    ],
    "country": "Portugal"
  },
  {
    "id": "20260209-lp1-porto-sporting",
    "sport": "Futebol",
    "competition": "Primeira Liga",
    "eventName": "FC Porto vs Sporting CP",
    "stage": "Liga regular",
    "startTimeUtc": "2026-02-09T20:45:00Z",
    "location": "Unknown",
    "channels": [
      {
        "name": "Sport TV 1",
        "type": "Subscription"
      }
    ],
    "country": "Portugal"
  },
  {
    "id": "20260209-seriea-atalanta-cremonese",
    "sport": "Futebol",
    "competition": "Serie A",
    "eventName": "Atalanta vs Cremonese",
    "stage": "Liga regular",
    "startTimeUtc": "2026-02-09T17:30:00Z",
    "location": "Unknown",
    "channels": [
      {
        "name": "Sport TV 2",
        "type": "Subscription"
      }
    ],
    "country": "Portugal"
  },
  {
    "id": "20260209-seriea-roma-salernitana",
    "sport": "Futebol",
    "competition": "Serie A",
    "eventName": "AS Roma vs Salernitana",
    "stage": "Liga regular",
    "startTimeUtc": "2026-02-09T19:45:00Z",
    "location": "Unknown",
    "channels": [
      {
        "name": "Sport TV 1",
        "type": "Subscription"
      }
    ],
    "country": "Portugal"
  },
  {
    "id": "20260210-coppaitalia-napoli-como",
    "sport": "Futebol",
    "competition": "Taça de Itália",
    "eventName": "Napoli vs Como",
    "stage": "Eliminatória",
    "startTimeUtc": "2026-02-10T20:00:00Z",
    "location": "Unknown",
    "channels": [
      {
        "name": "Sport TV 1",
        "type": "Subscription"
      }
    ],
    "country": "Portugal"
  },
  {
    "id": "20260211-coppaitalia-bologna-lazio",
    "sport": "Futebol",
    "competition": "Taça de Itália",
    "eventName": "Bologna vs Lazio",
    "stage": "Eliminatória",
    "startTimeUtc": "2026-02-11T20:00:00Z",
    "location": "Unknown",
    "channels": [
      {
        "name": "Sport TV 1",
        "type": "Subscription"
      }
    ],
    "country": "Portugal"
  }
]
